marsrouter/Router.py
marsrouter/__init__.py
MarsRouter-0.50.dist-info/LICENSE
MarsRouter-0.50.dist-info/METADATA
MarsRouter-0.50.dist-info/WHEEL
MarsRouter-0.50.dist-info/top_level.txt
MarsRouter-0.50.dist-info/RECORD
