Metadata-Version: 2.1
Name: MarsRouter
Version: 0.50
Summary: A batteries included web framework written in python
Author-email: Ahsan Ahmed <ahsan.ahmed3246@gmail.com>
Maintainer-email: Ahsan Ahmed <ahsan.ahmed3246@gmail.com>
License: MIT License
Project-URL: Homepage, https://github.com/MercuryFramework
Project-URL: Repository, https://github.com/MarsRouter/
Project-URL: Bug Tracker, https://github.com/MercuryFramework/MarsRouter/issues
Classifier: Intended Audience :: Information Technology
Classifier: Intended Audience :: System Administrators
Classifier: Operating System :: OS Independent
Classifier: Programming Language :: Python :: 3
Classifier: Programming Language :: Python
Classifier: Topic :: Internet
Classifier: Topic :: Software Development :: Libraries :: Application Frameworks
Classifier: Topic :: Software Development :: Libraries :: Python Modules
Classifier: Topic :: Software Development :: Libraries
Classifier: Topic :: Software Development
Classifier: Typing :: Typed
Classifier: Development Status :: 4 - Beta
Classifier: Environment :: Web Environment
Classifier: Intended Audience :: Developers
Classifier: License :: OSI Approved :: MIT License
Classifier: Programming Language :: Python :: 3 :: Only
Classifier: Programming Language :: Python :: 3.9
Classifier: Programming Language :: Python :: 3.10
Classifier: Programming Language :: Python :: 3.11
Classifier: Programming Language :: Python :: 3.12
Classifier: Topic :: Internet :: WWW/HTTP :: HTTP Servers
Classifier: Topic :: Internet :: WWW/HTTP
Requires-Python: >=3.8
License-File: LICENSE
